[
    {
        "Id": "1",
        "Job Title": "Software Developer",
        "Company Name": "TCS (Tata Consultancy Services)",
        "Address": "Mumbai, Maharashtra",
        "Required Skills": "Java, Spring Boot, SQL, REST APIs, Microservices",
        "Education": "B.E./B.Tech in Computer Science or IT",
        "Job Type": "Full-Time",
        "Shift": "Day Shift",
        "Job Description": "Design, develop, and maintain enterprise-level applications."
    },
    {
        "Id": "2",
        "Job Title": "Data Analyst",
        "Company Name": "Infosys",
        "Address": "Bengaluru, Karnataka",
        "Required Skills": "Python, SQL, Tableau, Power BI, Data Visualization",
        "Education": "B.Sc/B.Tech in Computer Science, Statistics, or related fields",
        "Job Type": "Full-Time",
        "Shift": "Day Shift",
        "Job Description": "Analyze business data, create reports, and generate insights."
    },
    {
        "Id": "3",
        "Job Title": "Digital Marketing Executive",
        "Company Name": "Wipro",
        "Address": "Hyderabad, Telangana",
        "Required Skills": "SEO, SEM, Social Media Marketing, Google Ads, Analytics",
        "Education": "MBA/PGDM in Marketing or related fields",
        "Job Type": "Full-Time",
        "Shift": "Rotational Shift",
        "Job Description": "Plan and execute digital marketing campaigns."
    },
    {
        "Id": "4",
        "Job Title": "HR Recruiter",
        "Company Name": "HCL Technologies",
        "Address": "Noida, Uttar Pradesh",
        "Required Skills": "Recruitment, Talent Acquisition, Communication, ATS Tools",
        "Education": "MBA in Human Resource Management",
        "Job Type": "Full-Time",
        "Shift": "Day Shift",
        "Job Description": "Manage end-to-end recruitment process."
    },
    {
        "Id": "5",
        "Job Title": "Mechanical Engineer",
        "Company Name": "Larsen & Toubro (L&T)",
        "Address": "Chennai, Tamil Nadu",
        "Required Skills": "AutoCAD, SolidWorks, Manufacturing Processes, Quality Control",
        "Education": "B.E./B.Tech in Mechanical Engineering",
        "Job Type": "Full-Time",
        "Shift": "Day Shift",
        "Job Description": "Design and oversee mechanical systems manufacturing."
    },
    {
        "Id": "6",
        "Job Title": "Cloud Engineer",
        "Company Name": "Tech Mahindra",
        "Address": "Pune, Maharashtra",
        "Required Skills": "AWS, Azure, Docker, Kubernetes, Terraform",
        "Education": "B.E./B.Tech in Computer Science or IT",
        "Job Type": "Full-Time",
        "Shift": "Day Shift",
        "Job Description": "Design and implement cloud-based solutions."
    },
    {
        "Id": "7",
        "Job Title": "Business Analyst",
        "Company Name": "Accenture",
        "Address": "Gurugram, Haryana",
        "Required Skills": "Business Intelligence, SQL, Data Analytics, Agile Methodologies",
        "Education": "MBA or Bachelor's in Business Administration",
        "Job Type": "Full-Time",
        "Shift": "Day Shift",
        "Job Description": "Analyze business processes and recommend solutions."
    },
    {
        "Id": "8",
        "Job Title": "Graphic Designer",
        "Company Name": "Zomato",
        "Address": "New Delhi",
        "Required Skills": "Adobe Photoshop, Illustrator, Figma, Canva, UI/UX Design",
        "Education": "Bachelor’s in Graphic Design or Fine Arts",
        "Job Type": "Contract",
        "Shift": "Flexible",
        "Job Description": "Create visually appealing designs for digital and print media."
    },
    {
        "Id": "9",
        "Job Title": "Cyber Security Analyst",
        "Company Name": "Cognizant",
        "Address": "Chennai, Tamil Nadu",
        "Required Skills": "Network Security, Ethical Hacking, Penetration Testing, SIEM Tools",
        "Education": "B.Tech/B.E. in Cyber Security or Information Security",
        "Job Type": "Full-Time",
        "Shift": "Rotational Shift",
        "Job Description": "Monitor and prevent cybersecurity threats."
    },
    {
        "Id": "10",
        "Job Title": "Civil Engineer",
        "Company Name": "Godrej Properties",
        "Address": "Bangalore, Karnataka",
        "Required Skills": "AutoCAD, STAAD Pro, Structural Design, Construction Management",
        "Education": "B.Tech/B.E. in Civil Engineering",
        "Job Type": "Full-Time",
        "Shift": "Day Shift",
        "Job Description": "Oversee construction projects and ensure timely completion."
    },
    {
        "Id": "11",
        "Job Title": "Content Writer",
        "Company Name": "Byju’s",
        "Address": "Bengaluru, Karnataka",
        "Required Skills": "SEO Writing, Blogging, Copywriting, Proofreading, Content Strategy",
        "Education": "Bachelor’s in English, Journalism, or Mass Communication",
        "Job Type": "Full-Time",
        "Shift": "Day Shift",
        "Job Description": "Create engaging content for educational platforms."
    },
    {
        "Id": "12",
        "Job Title": "Artificial Intelligence Engineer",
        "Company Name": "Reliance Jio",
        "Address": "Navi Mumbai, Maharashtra",
        "Required Skills": "Machine Learning, Deep Learning, Python, TensorFlow, NLP",
        "Education": "B.E./B.Tech/M.Tech in AI, Data Science, or related field",
        "Job Type": "Full-Time",
        "Shift": "Day Shift",
        "Job Description": "Develop and deploy AI-driven solutions."
    },
    {
        "Id": "13",
        "Job Title": "Sales Executive",
        "Company Name": "Paytm",
        "Address": "Lucknow, Uttar Pradesh",
        "Required Skills": "Sales, Negotiation, Customer Relationship, CRM Software",
        "Education": "MBA/BBA in Sales & Marketing",
        "Job Type": "Full-Time",
        "Shift": "Day Shift",
        "Job Description": "Acquire customers, promote digital payment solutions."
    },
    {
        "Id": "14",
        "Job Title": "Pharmacist",
        "Company Name": "Apollo Hospitals",
        "Address": "Hyderabad, Telangana",
        "Required Skills": "Pharmacology, Drug Dispensing, Medical Compliance, Inventory Management",
        "Education": "B.Pharm/M.Pharm in Pharmacy",
        "Job Type": "Full-Time",
        "Shift": "Rotational Shift",
        "Job Description": "Manage prescriptions and medication counseling."
    },
    {
        "Id": "15",
        "Job Title": "UI/UX Designer",
        "Company Name": "Flipkart",
        "Address": "Bangalore, Karnataka",
        "Required Skills": "Figma, Adobe XD, Wireframing, User Research, Prototyping",
        "Education": "Bachelor’s in Design, UI/UX, or related field",
        "Job Type": "Full-Time",
        "Shift": "Day Shift",
        "Job Description": "Create user-friendly designs for e-commerce platforms."
    },
    {
        "Id": "16",
        "Job Title": "Software Developer",
        "Company Name": "TCS (Tata Consultancy Services)",
        "Address": "Mumbai, Maharashtra",
        "Required Skills": "Java, Spring Boot, SQL, REST APIs, Microservices",
        "Education": "B.E./B.Tech in Computer Science or IT",
        "Job Type": "Full-Time",
        "Shift": "Day Shift",
        "Job Description": "Design, develop, and maintain enterprise-level applications."
    },
    {
        "Id": "17",
        "Job Title": "Data Analyst",
        "Company Name": "Infosys",
        "Address": "Bengaluru, Karnataka",
        "Required Skills": "Python, SQL, Tableau, Power BI, Data Visualization",
        "Education": "B.Sc/B.Tech in Computer Science, Statistics, or related fields",
        "Job Type": "Full-Time",
        "Shift": "Day Shift",
        "Job Description": "Analyze business data, create reports, and generate insights."
    },
    {
        "Id": "18",
        "Job Title": "Digital Marketing Executive",
        "Company Name": "Wipro",
        "Address": "Hyderabad, Telangana",
        "Required Skills": "SEO, SEM, Social Media Marketing, Google Ads, Analytics",
        "Education": "MBA/PGDM in Marketing or related fields",
        "Job Type": "Full-Time",
        "Shift": "Rotational Shift",
        "Job Description": "Plan and execute digital marketing campaigns."
    },
    {
        "Id": "19",
        "Job Title": "HR Recruiter",
        "Company Name": "HCL Technologies",
        "Address": "Noida, Uttar Pradesh",
        "Required Skills": "Recruitment, Talent Acquisition, Communication, ATS Tools",
        "Education": "MBA in Human Resource Management",
        "Job Type": "Full-Time",
        "Shift": "Day Shift",
        "Job Description": "Manage end-to-end recruitment process."
    },
    {
        "Id": "20",
        "Job Title": "Mechanical Engineer",
        "Company Name": "Larsen & Toubro (L&T)",
        "Address": "Chennai, Tamil Nadu",
        "Required Skills": "AutoCAD, SolidWorks, Manufacturing Processes, Quality Control",
        "Education": "B.E./B.Tech in Mechanical Engineering",
        "Job Type": "Full-Time",
        "Shift": "Day Shift",
        "Job Description": "Design and oversee mechanical systems manufacturing."
    },
    {
        "Id": "21",
        "Job Title": "Cloud Engineer",
        "Company Name": "Tech Mahindra",
        "Address": "Pune, Maharashtra",
        "Required Skills": "AWS, Azure, Docker, Kubernetes, Terraform",
        "Education": "B.E./B.Tech in Computer Science or IT",
        "Job Type": "Full-Time",
        "Shift": "Day Shift",
        "Job Description": "Design and implement cloud-based solutions."
    },
    {
        "Id": "22",
        "Job Title": "Business Analyst",
        "Company Name": "Accenture",
        "Address": "Gurugram, Haryana",
        "Required Skills": "Business Intelligence, SQL, Data Analytics, Agile Methodologies",
        "Education": "MBA or Bachelor's in Business Administration",
        "Job Type": "Full-Time",
        "Shift": "Day Shift",
        "Job Description": "Analyze business processes and recommend solutions."
    },
    {
        "Id": "23",
        "Job Title": "Graphic Designer",
        "Company Name": "Zomato",
        "Address": "New Delhi",
        "Required Skills": "Adobe Photoshop, Illustrator, Figma, Canva, UI/UX Design",
        "Education": "Bachelor’s in Graphic Design or Fine Arts",
        "Job Type": "Contract",
        "Shift": "Flexible",
        "Job Description": "Create visually appealing designs for digital and print media."
    },
    {
        "Id": "24",
        "Job Title": "Cyber Security Analyst",
        "Company Name": "Cognizant",
        "Address": "Chennai, Tamil Nadu",
        "Required Skills": "Network Security, Ethical Hacking, Penetration Testing, SIEM Tools",
        "Education": "B.Tech/B.E. in Cyber Security or Information Security",
        "Job Type": "Full-Time",
        "Shift": "Rotational Shift",
        "Job Description": "Monitor and prevent cybersecurity threats."
    },
    {
        "Id": "25",
        "Job Title": "Civil Engineer",
        "Company Name": "Godrej Properties",
        "Address": "Bangalore, Karnataka",
        "Required Skills": "AutoCAD, STAAD Pro, Structural Design, Construction Management",
        "Education": "B.Tech/B.E. in Civil Engineering",
        "Job Type": "Full-Time",
        "Shift": "Day Shift",
        "Job Description": "Oversee construction projects and ensure timely completion."
    },
    {
        "Id": "26",
        "Job Title": "Content Writer",
        "Company Name": "Byju’s",
        "Address": "Bengaluru, Karnataka",
        "Required Skills": "SEO Writing, Blogging, Copywriting, Proofreading, Content Strategy",
        "Education": "Bachelor’s in English, Journalism, or Mass Communication",
        "Job Type": "Full-Time",
        "Shift": "Day Shift",
        "Job Description": "Create engaging content for educational platforms."
    },
    {
        "Id": "27",
        "Job Title": "Artificial Intelligence Engineer",
        "Company Name": "Reliance Jio",
        "Address": "Navi Mumbai, Maharashtra",
        "Required Skills": "Machine Learning, Deep Learning, Python, TensorFlow, NLP",
        "Education": "B.E./B.Tech/M.Tech in AI, Data Science, or related field",
        "Job Type": "Full-Time",
        "Shift": "Day Shift",
        "Job Description": "Develop and deploy AI-driven solutions."
    },
    {
        "Id": "28",
        "Job Title": "Sales Executive",
        "Company Name": "Paytm",
        "Address": "Lucknow, Uttar Pradesh",
        "Required Skills": "Sales, Negotiation, Customer Relationship, CRM Software",
        "Education": "MBA/BBA in Sales & Marketing",
        "Job Type": "Full-Time",
        "Shift": "Day Shift",
        "Job Description": "Acquire customers, promote digital payment solutions."
    },
    {
        "Id": "29",
        "Job Title": "Pharmacist",
        "Company Name": "Apollo Hospitals",
        "Address": "Hyderabad, Telangana",
        "Required Skills": "Pharmacology, Drug Dispensing, Medical Compliance, Inventory Management",
        "Education": "B.Pharm/M.Pharm in Pharmacy",
        "Job Type": "Full-Time",
        "Shift": "Rotational Shift",
        "Job Description": "Manage prescriptions and medication counseling."
    },
    {
        "Id": "30",
        "Job Title": "UI/UX Designer",
        "Company Name": "Flipkart",
        "Address": "Bangalore, Karnataka",
        "Required Skills": "Figma, Adobe XD, Wireframing, User Research, Prototyping",
        "Education": "Bachelor’s in Design, UI/UX, or related field",
        "Job Type": "Full-Time",
        "Shift": "Day Shift",
        "Job Description": "Create user-friendly designs for e-commerce platforms."
    },
    {
        "Id": "31",
        "Job Title": "Software Developer",
        "Company Name": "TCS (Tata Consultancy Services)",
        "Address": "Mumbai, Maharashtra",
        "Required Skills": "Java, Spring Boot, SQL, REST APIs, Microservices",
        "Education": "B.E./B.Tech in Computer Science or IT",
        "Job Type": "Full-Time",
        "Shift": "Day Shift",
        "Job Description": "Design, develop, and maintain enterprise-level applications."
    },
    {
        "Id": "32",
        "Job Title": "Data Analyst",
        "Company Name": "Infosys",
        "Address": "Bengaluru, Karnataka",
        "Required Skills": "Python, SQL, Tableau, Power BI, Data Visualization",
        "Education": "B.Sc/B.Tech in Computer Science, Statistics, or related fields",
        "Job Type": "Full-Time",
        "Shift": "Day Shift",
        "Job Description": "Analyze business data, create reports, and generate insights."
    },
    {
        "Id": "33",
        "Job Title": "Digital Marketing Executive",
        "Company Name": "Wipro",
        "Address": "Hyderabad, Telangana",
        "Required Skills": "SEO, SEM, Social Media Marketing, Google Ads, Analytics",
        "Education": "MBA/PGDM in Marketing or related fields",
        "Job Type": "Full-Time",
        "Shift": "Rotational Shift",
        "Job Description": "Plan and execute digital marketing campaigns."
    },
    {
        "Id": "34",
        "Job Title": "HR Recruiter",
        "Company Name": "HCL Technologies",
        "Address": "Noida, Uttar Pradesh",
        "Required Skills": "Recruitment, Talent Acquisition, Communication, ATS Tools",
        "Education": "MBA in Human Resource Management",
        "Job Type": "Full-Time",
        "Shift": "Day Shift",
        "Job Description": "Manage end-to-end recruitment process."
    },
    {
        "Id": "35",
        "Job Title": "Mechanical Engineer",
        "Company Name": "Larsen & Toubro (L&T)",
        "Address": "Chennai, Tamil Nadu",
        "Required Skills": "AutoCAD, SolidWorks, Manufacturing Processes, Quality Control",
        "Education": "B.E./B.Tech in Mechanical Engineering",
        "Job Type": "Full-Time",
        "Shift": "Day Shift",
        "Job Description": "Design and oversee mechanical systems manufacturing."
    },
    {
        "Id": "36",
        "Job Title": "Cloud Engineer",
        "Company Name": "Tech Mahindra",
        "Address": "Pune, Maharashtra",
        "Required Skills": "AWS, Azure, Docker, Kubernetes, Terraform",
        "Education": "B.E./B.Tech in Computer Science or IT",
        "Job Type": "Full-Time",
        "Shift": "Day Shift",
        "Job Description": "Design and implement cloud-based solutions."
    },
    {
        "Id": "37",
        "Job Title": "Business Analyst",
        "Company Name": "Accenture",
        "Address": "Gurugram, Haryana",
        "Required Skills": "Business Intelligence, SQL, Data Analytics, Agile Methodologies",
        "Education": "MBA or Bachelor's in Business Administration",
        "Job Type": "Full-Time",
        "Shift": "Day Shift",
        "Job Description": "Analyze business processes and recommend solutions."
    },
    {
        "Id": "38",
        "Job Title": "Graphic Designer",
        "Company Name": "Zomato",
        "Address": "New Delhi",
        "Required Skills": "Adobe Photoshop, Illustrator, Figma, Canva, UI/UX Design",
        "Education": "Bachelor’s in Graphic Design or Fine Arts",
        "Job Type": "Contract",
        "Shift": "Flexible",
        "Job Description": "Create visually appealing designs for digital and print media."
    },
    {
        "Id": "39",
        "Job Title": "Cyber Security Analyst",
        "Company Name": "Cognizant",
        "Address": "Chennai, Tamil Nadu",
        "Required Skills": "Network Security, Ethical Hacking, Penetration Testing, SIEM Tools",
        "Education": "B.Tech/B.E. in Cyber Security or Information Security",
        "Job Type": "Full-Time",
        "Shift": "Rotational Shift",
        "Job Description": "Monitor and prevent cybersecurity threats."
    },
    {
        "Id": "40",
        "Job Title": "Civil Engineer",
        "Company Name": "Godrej Properties",
        "Address": "Bangalore, Karnataka",
        "Required Skills": "AutoCAD, STAAD Pro, Structural Design, Construction Management",
        "Education": "B.Tech/B.E. in Civil Engineering",
        "Job Type": "Full-Time",
        "Shift": "Day Shift",
        "Job Description": "Oversee construction projects and ensure timely completion."
    },
    {
        "Id": "41",
        "Job Title": "Content Writer",
        "Company Name": "Byju’s",
        "Address": "Bengaluru, Karnataka",
        "Required Skills": "SEO Writing, Blogging, Copywriting, Proofreading, Content Strategy",
        "Education": "Bachelor’s in English, Journalism, or Mass Communication",
        "Job Type": "Full-Time",
        "Shift": "Day Shift",
        "Job Description": "Create engaging content for educational platforms."
    },
    {
        "Id": "42",
        "Job Title": "Artificial Intelligence Engineer",
        "Company Name": "Reliance Jio",
        "Address": "Navi Mumbai, Maharashtra",
        "Required Skills": "Machine Learning, Deep Learning, Python, TensorFlow, NLP",
        "Education": "B.E./B.Tech/M.Tech in AI, Data Science, or related field",
        "Job Type": "Full-Time",
        "Shift": "Day Shift",
        "Job Description": "Develop and deploy AI-driven solutions."
    },
    {
        "Id": "43",
        "Job Title": "Sales Executive",
        "Company Name": "Paytm",
        "Address": "Lucknow, Uttar Pradesh",
        "Required Skills": "Sales, Negotiation, Customer Relationship, CRM Software",
        "Education": "MBA/BBA in Sales & Marketing",
        "Job Type": "Full-Time",
        "Shift": "Day Shift",
        "Job Description": "Acquire customers, promote digital payment solutions."
    },
    {
        "Id": "44",
        "Job Title": "Pharmacist",
        "Company Name": "Apollo Hospitals",
        "Address": "Hyderabad, Telangana",
        "Required Skills": "Pharmacology, Drug Dispensing, Medical Compliance, Inventory Management",
        "Education": "B.Pharm/M.Pharm in Pharmacy",
        "Job Type": "Full-Time",
        "Shift": "Rotational Shift",
        "Job Description": "Manage prescriptions and medication counseling."
    },
    {
        "Id": "45",
        "Job Title": "UI/UX Designer",
        "Company Name": "Flipkart",
        "Address": "Bangalore, Karnataka",
        "Required Skills": "Figma, Adobe XD, Wireframing, User Research, Prototyping",
        "Education": "Bachelor’s in Design, UI/UX, or related field",
        "Job Type": "Full-Time",
        "Shift": "Day Shift",
        "Job Description": "Create user-friendly designs for e-commerce platforms."
    },
    {
        "Id": "46",
        "Job Title": "Electrical Engineer",
        "Company Name": "Siemens",
        "Address": "Pune, Maharashtra",
        "Required Skills": "Circuit Design, Power Systems, AutoCAD, MATLAB",
        "Education": "B.E./B.Tech in Electrical Engineering",
        "Job Type": "Full-Time",
        "Shift": "Day Shift",
        "Job Description": "Design and analyze electrical systems for industrial applications."
    },
    {
        "Id": "47",
        "Job Title": "Backend Developer",
        "Company Name": "Amazon India",
        "Address": "Hyderabad, Telangana",
        "Required Skills": "Node.js, Express.js, MongoDB, AWS, Docker",
        "Education": "B.E./B.Tech in Computer Science or IT",
        "Job Type": "Full-Time",
        "Shift": "Day Shift",
        "Job Description": "Develop and maintain scalable backend services."
    },
    {
        "Id": "48",
        "Job Title": "Front-end Developer",
        "Company Name": "Google India",
        "Address": "Bangalore, Karnataka",
        "Required Skills": "React.js, JavaScript, CSS, HTML, UI Design",
        "Education": "B.E./B.Tech in Computer Science or IT",
        "Job Type": "Full-Time",
        "Shift": "Day Shift",
        "Job Description": "Build interactive and responsive web applications."
    },
    {
        "Id": "49",
        "Job Title": "Blockchain Developer",
        "Company Name": "Polygon",
        "Address": "Mumbai, Maharashtra",
        "Required Skills": "Solidity, Ethereum, Smart Contracts, Web3.js",
        "Education": "B.E./B.Tech in Computer Science or IT",
        "Job Type": "Full-Time",
        "Shift": "Day Shift",
        "Job Description": "Develop and optimize blockchain applications."
    },
    {
        "Id": "50",
        "Job Title": "Game Developer",
        "Company Name": "Ubisoft India",
        "Address": "Pune, Maharashtra",
        "Required Skills": "Unity, C#, Unreal Engine, Game Physics",
        "Education": "B.E./B.Tech in Computer Science or Game Development",
        "Job Type": "Full-Time",
        "Shift": "Day Shift",
        "Job Description": "Design and develop engaging video games."
    }
]